{
    "name": "gaming pfp 1",
    "description": "A unique piece of gaming nft1.",
    "image": "https://maroon-annoyed-dinosaur-120.mypinata.cloud/ipfs/QmRuwByPWCtVtjEBjpx1BJAtWAEqaTZE4ExpjsvFgbb3r5"
}
{
    "name": "gaming pfp 2",
    "description": "A unique piece of gaming nft2.",
    "image": "https://maroon-annoyed-dinosaur-120.mypinata.cloud/ipfs/QmS6cbPtLeXMtrrTW7ymTWZzXaRo1n73Yowi4FW2cLAmN3"
}
{
    "name": "gaming pfp 3",
    "description": "A unique piece of gaming nft3.",
    "image": "https://maroon-annoyed-dinosaur-120.mypinata.cloud/ipfs/QmawGWK5ZL35BpWEBHUyAAttE1PwZiEe41EMCQUV3v2rcu"
}